{
  "unique_id": "2tIO60Ho",
  "path": "radio.tpl",
  "completePath": "C:\\Users\\Ines\\Aptugo\\templates\\5ec1574d22999c4a5e8e0dc7\\elements\\Material-UI\\Forms\\radio.tpl",
  "keyPath": "elements\\Material-UI\\Forms\\radio.tpl",
  "type": "element",
  "icon": "f:radio.svg",
  "options": [
    {
      "name": "checked",
      "display": "Checked",
      "type": "text",
      "options": ""
    },
    {
      "name": "onchange",
      "display": "On Change",
      "type": "text",
      "options": ""
    },
    {
      "name": "value",
      "display": "Value",
      "type": "text",
      "options": ""
    },
    {
      "name": "name",
      "display": "Name",
      "type": "text",
      "options": ""
    },
    {
      "name": "label",
      "display": "label",
      "type": "text",
      "options": ""
    }
  ],
  "name": "Femenino",
  "prevent_delete": false,
  "cascades": false,
  "parent": "xOMzzfId",
  "value": "radio",
  "values": {
    "value": "{usName}",
    "label": "Femenino"
  },
  "collapseStatus": "expand",
  "errored": false
}